{
  "unversionedId": "pythonapi",
  "id": "pythonapi",
  "title": "Python Reference",
  "description": "* uclchem",
  "source": "@site/docs/start-pythonapi.md",
  "sourceDirName": ".",
  "slug": "/pythonapi",
  "permalink": "/docs/next/pythonapi",
  "draft": false,
  "tags": [],
  "version": "current",
  "lastUpdatedBy": "Gijs Vermariën",
  "lastUpdatedAt": 1693569187,
  "formattedLastUpdatedAt": "Sep 1, 2023",
  "frontMatter": {
    "id": "pythonapi",
    "title": "Python Reference"
  },
  "sidebar": "docs",
  "previous": {
    "title": "Model Parameters",
    "permalink": "/docs/next/parameters"
  },
  "next": {
    "title": "Tutorials",
    "permalink": "/docs/next/category/tutorials"
  }
}